LICENSE
MANIFEST.in
README.rst
helga_crickets.py
setup.py
helga_crickets.egg-info/PKG-INFO
helga_crickets.egg-info/SOURCES.txt
helga_crickets.egg-info/dependency_links.txt
helga_crickets.egg-info/entry_points.txt
helga_crickets.egg-info/top_level.txt
helga_crickets.egg-info/zip-safe