Metadata-Version: 1.0
Name: helga-crickets
Version: 0.0.3
Summary: Helga plugin that will respond with the word cricketsafter a question has gone unacknowledged for a configurable amount of time.
Home-page: https://github.com/shaunduncan/helga-crickets
Author: Shaun Duncan
Author-email: shaun.duncan@gmail.com
License: UNKNOWN
Platform: UNKNOWN
